tear/FineTunedBertModule.py
tear/__main__.py
tear/earthquakeReport.py
tear/earthquake_data.py
tear/summarize.py
tear/usgsModule.py
tear/website2text.py
tear-0.0.2.dist-info/METADATA
tear-0.0.2.dist-info/WHEEL
tear-0.0.2.dist-info/entry_points.txt
tear-0.0.2.dist-info/top_level.txt
tear-0.0.2.dist-info/RECORD
